{
  "version": 0,
  "families": {
    "sword": {
      "icon": { "shape": "blade", "color": "#b8bdc2", "accent": "#6d5a3a", "label": "Sw" },
      "ground": { "shape": "blade", "color": "#b8bdc2", "accent": "#6d5a3a", "scale": 1.0 },
      "3d_model": "weapon_rusty_sword_v0"
    },
    "greatsword": {
      "icon": { "shape": "blade", "color": "#9a8f86", "accent": "#f0d7a0", "label": "2H" },
      "ground": { "shape": "blade", "color": "#9a8f86", "accent": "#f0d7a0", "scale": 1.1 },
      "3d_model": "weapon_rusty_sword_v0"
    },
    "axe": {
      "icon": { "shape": "blade", "color": "#b85f48", "accent": "#ffd0a3", "label": "Ax" },
      "ground": { "shape": "blade", "color": "#b85f48", "accent": "#ffd0a3", "scale": 1.05 },
      "3d_model": "weapon_starter_axe_v0"
    },
    "staff": {
      "icon": { "shape": "blade", "color": "#5e8fd6", "accent": "#d8f0ff", "label": "St" },
      "ground": { "shape": "blade", "color": "#5e8fd6", "accent": "#d8f0ff", "scale": 1.1 },
      "3d_model": "weapon_starter_staff_v0"
    },
    "bow": {
      "icon": { "shape": "bow", "color": "#9b6a3c", "accent": "#d8c17b", "label": "Bw" },
      "ground": { "shape": "bow", "color": "#9b6a3c", "accent": "#d8c17b", "scale": 1.0 },
      "3d_model": "weapon_training_bow_v0"
    },
    "shield": {
      "icon": { "shape": "shield", "color": "#677489", "accent": "#cbd4df", "label": "Sh" },
      "ground": { "shape": "shield", "color": "#677489", "accent": "#cbd4df", "scale": 1.0 },
      "3d_model": "fallback_equipment_off_hand_v0"
    },
    "helm": {
      "icon": { "shape": "helm", "color": "#6f7780", "accent": "#e0e5e8", "label": "Hm" },
      "ground": { "shape": "helm", "color": "#6f7780", "accent": "#e0e5e8", "scale": 0.9 },
      "3d_model": "fallback_equipment_head_v0"
    },
    "chest": {
      "icon": { "shape": "chest", "color": "#626b73", "accent": "#d7dde2", "label": "Ml" },
      "ground": { "shape": "chest", "color": "#626b73", "accent": "#d7dde2", "scale": 1.0 },
      "3d_model": "fallback_equipment_chest_v0"
    },
    "gloves": {
      "icon": { "shape": "gloves", "color": "#736252", "accent": "#dcc6a8", "label": "Gl" },
      "ground": { "shape": "gloves", "color": "#736252", "accent": "#dcc6a8", "scale": 0.8 },
      "3d_model": "fallback_equipment_gloves_v0"
    },
    "belt": {
      "icon": { "shape": "belt", "color": "#7f5a35", "accent": "#e6c086", "label": "Bt" },
      "ground": { "shape": "belt", "color": "#7f5a35", "accent": "#e6c086", "scale": 0.8 },
      "3d_model": "fallback_equipment_belt_v0"
    },
    "boots": {
      "icon": { "shape": "boots", "color": "#514f4b", "accent": "#c4b9a5", "label": "Bo" },
      "ground": { "shape": "boots", "color": "#514f4b", "accent": "#c4b9a5", "scale": 0.8 },
      "3d_model": "fallback_equipment_boots_v0"
    },
    "ring": {
      "icon": { "shape": "ring", "color": "#d1b457", "accent": "#fff1a8", "label": "Rg" },
      "ground": { "shape": "ring", "color": "#d1b457", "accent": "#fff1a8", "scale": 0.7 },
      "3d_model": "fallback_equipment_ring_left_v0"
    },
    "amulet": {
      "icon": { "shape": "amulet", "color": "#6aa7b8", "accent": "#d8f4ff", "label": "Am" },
      "ground": { "shape": "amulet", "color": "#6aa7b8", "accent": "#d8f4ff", "scale": 0.7 },
      "3d_model": "fallback_equipment_amulet_v0"
    },
    "gold": {
      "icon": { "shape": "coin", "color": "#d5a928", "accent": "#fff0a6", "label": "Au" },
      "ground": { "shape": "coin", "color": "#d5a928", "accent": "#fff0a6", "scale": 0.9 }
    },
    "quest": {
      "icon": { "shape": "leaf", "color": "#3fbf62", "accent": "#b8f0a8", "label": "Lf" },
      "ground": { "shape": "leaf", "color": "#3fbf62", "accent": "#b8f0a8", "scale": 0.9 }
    },
    "health_potion": {
      "icon": { "shape": "potion", "color": "#d63b32", "accent": "#ffd3c9", "label": "Pt" },
      "ground": { "shape": "potion", "color": "#d63b32", "accent": "#ffd3c9", "scale": 0.9 }
    },
    "mana_potion": {
      "icon": { "shape": "potion", "color": "#42b9e8", "accent": "#d8f7ff", "label": "Mn" },
      "ground": { "shape": "potion", "color": "#42b9e8", "accent": "#d8f7ff", "scale": 0.9 }
    }
  },
  "items": {
    "rusty_sword": { "family": "sword" },
    "cave_blade": {
      "family": "sword",
      "icon": { "shape": "blade", "color": "#78a7b8", "accent": "#d8f0ff", "label": "CB" },
      "ground": { "shape": "blade", "color": "#78a7b8", "accent": "#d8f0ff", "scale": 1.0 }
    },
    "starter_paladin_sword": {
      "family": "sword",
      "icon": { "shape": "blade", "color": "#d1b457", "accent": "#fff1a8", "label": "Sw" },
      "ground": { "shape": "blade", "color": "#d1b457", "accent": "#fff1a8", "scale": 1.0 }
    },
    "starter_paladin_shield": {
      "family": "shield",
      "icon": { "shape": "shield", "color": "#9b8b4d", "accent": "#fff1a8", "label": "Sh" },
      "ground": { "shape": "shield", "color": "#9b8b4d", "accent": "#fff1a8", "scale": 1.0 }
    },
    "starter_sorcerer_staff": { "family": "staff" },
    "starter_barbarian_axe": {
      "family": "axe",
      "ground": { "shape": "blade", "color": "#b85f48", "accent": "#ffd0a3", "scale": 1.1 }
    },
    "training_bow": { "family": "bow" },
    "barbarian_axe": { "family": "axe" },
    "sorcerer_staff": { "family": "staff" },
    "paladin_mace": {
      "family": "sword",
      "icon": { "shape": "blade", "color": "#d1b457", "accent": "#fff1a8", "label": "Mc" },
      "ground": { "shape": "blade", "color": "#d1b457", "accent": "#fff1a8", "scale": 1.05 }
    },
    "cave_greatsword": { "family": "greatsword" },
    "cave_war_sword": {
      "family": "sword",
      "icon": { "shape": "blade", "color": "#a57458", "accent": "#ffd0a3", "label": "WS" },
      "ground": { "shape": "blade", "color": "#a57458", "accent": "#ffd0a3", "scale": 1.05 }
    },
    "cave_bow": {
      "family": "bow",
      "icon": { "shape": "bow", "color": "#8f6b42", "accent": "#e6c27b", "label": "CB" },
      "ground": { "shape": "bow", "color": "#8f6b42", "accent": "#e6c27b", "scale": 1.0 }
    },
    "cave_shield": { "family": "shield" },
    "cave_helm": { "family": "helm" },
    "cave_mail": { "family": "chest" },
    "cave_gloves": { "family": "gloves" },
    "cave_belt": { "family": "belt" },
    "cave_pack_belt": {
      "family": "belt",
      "icon": { "shape": "belt", "color": "#5f7043", "accent": "#d2e6a4", "label": "Pk" },
      "ground": { "shape": "belt", "color": "#5f7043", "accent": "#d2e6a4", "scale": 0.8 }
    },
    "cave_boots": { "family": "boots" },
    "cave_ring": { "family": "ring" },
    "cave_amulet": { "family": "amulet" },
    "gold": { "family": "gold" },
    "quest_leaf": { "family": "quest" },
    "red_potion": { "family": "health_potion" },
    "blue_potion": { "family": "mana_potion" }
  }
}
